streetscapes/__init__.py
streetscapes/main.py
streetscapes/models/__init__.py
streetscapes/models/base.py
streetscapes/models/dinosam.py
streetscapes/models/maskformer.py
streetscapes/sources/__init__.py
streetscapes/sources/base.py
streetscapes/sources/hf/__init__.py
streetscapes/sources/hf/base.py
streetscapes/sources/hf/global_streetscapes.py
streetscapes/sources/image/__init__.py
streetscapes/sources/image/amsterdam.py
streetscapes/sources/image/base.py
streetscapes/sources/image/google.py
streetscapes/sources/image/kartaview.py
streetscapes/sources/image/mapillary.py
streetscapes/streetview/__init__.py
streetscapes/streetview/image.py
streetscapes/streetview/imageset.py
streetscapes/streetview/instance.py
streetscapes/streetview/segmentation.py
streetscapes/streetview/workspace.py
streetscapes/utils/__init__.py
streetscapes/utils/functions.py
streetscapes/utils/logging.py
streetscapes-0.3.2.dist-info/licenses/LICENCE.md
streetscapes-0.3.2.dist-info/METADATA
streetscapes-0.3.2.dist-info/WHEEL
streetscapes-0.3.2.dist-info/entry_points.txt
streetscapes-0.3.2.dist-info/top_level.txt
streetscapes-0.3.2.dist-info/RECORD
