Metadata-Version: 2.4
Name: streetscapes
Version: 0.3.2
Summary: Code for downloading, segmenting and analysing images from Mapillary and KartaView, with the aim of extracting the emissivity and albedo of buildings.
Author-email: Claire Donnelly <c.donnelly@esciencecenter.nl>, Alexander Hadjiivanov <a.hadjiivanov@esciencecenter.nl>, Peter Kalverla <p.kalverla@esciencecenter.nl>
License: Attribution-ShareAlike 4.0 International
Requires-Python: >=3.11
License-File: LICENCE.md
Requires-Dist: awkward
Requires-Dist: black
Requires-Dist: cloup
Requires-Dist: contextily
Requires-Dist: duckdb
Requires-Dist: ephem
Requires-Dist: environs
Requires-Dist: fiona
Requires-Dist: geodatasets
Requires-Dist: geopandas
Requires-Dist: h3
Requires-Dist: h5netcdf
Requires-Dist: humanize
Requires-Dist: huggingface_hub[cli]
Requires-Dist: ibis-framework[duckdb]
Requires-Dist: ipykernel
Requires-Dist: ipywidgets
Requires-Dist: loguru
Requires-Dist: matplotlib
Requires-Dist: numpy
Requires-Dist: osmnx
Requires-Dist: pandas
Requires-Dist: pyarrow
Requires-Dist: pyproj
Requires-Dist: rasterio
Requires-Dist: rich
Requires-Dist: sam2
Requires-Dist: seedir
Requires-Dist: scikit-image
Requires-Dist: scipy
Requires-Dist: timezonefinder
Requires-Dist: torch
Requires-Dist: torchvision
Requires-Dist: tqdm
Requires-Dist: transformers
Provides-Extra: dev
Requires-Dist: ruff; extra == "dev"
Requires-Dist: py-spy; extra == "dev"
Requires-Dist: mike; extra == "dev"
Requires-Dist: mkdocs; extra == "dev"
Requires-Dist: mkdocstrings[python]; extra == "dev"
Requires-Dist: mkdocs-material; extra == "dev"
Requires-Dist: mkdocs-jupyter; extra == "dev"
Dynamic: license-file
